odoo/addons/product_variant_change_attribute_value/README.rst
odoo/addons/product_variant_change_attribute_value/__init__.py
odoo/addons/product_variant_change_attribute_value/__manifest__.py
odoo/addons/product_variant_change_attribute_value/demo/product_demo.xml
odoo/addons/product_variant_change_attribute_value/i18n/it.po
odoo/addons/product_variant_change_attribute_value/i18n/product_variant_change_attribute_value.pot
odoo/addons/product_variant_change_attribute_value/readme/CONTRIBUTORS.md
odoo/addons/product_variant_change_attribute_value/readme/CREDITS.md
odoo/addons/product_variant_change_attribute_value/readme/DESCRIPTION.md
odoo/addons/product_variant_change_attribute_value/readme/ROADMAP.md
odoo/addons/product_variant_change_attribute_value/readme/USAGE.md
odoo/addons/product_variant_change_attribute_value/security/ir.model.access.csv
odoo/addons/product_variant_change_attribute_value/static/description/icon.png
odoo/addons/product_variant_change_attribute_value/static/description/index.html
odoo/addons/product_variant_change_attribute_value/tests/__init__.py
odoo/addons/product_variant_change_attribute_value/tests/test_product_variant_change_attribute_value.py
odoo/addons/product_variant_change_attribute_value/wizards/__init__.py
odoo/addons/product_variant_change_attribute_value/wizards/product_variant_attribute_value_action.py
odoo/addons/product_variant_change_attribute_value/wizards/product_variant_attribute_value_wizard.py
odoo/addons/product_variant_change_attribute_value/wizards/product_variant_attribute_value_wizard.xml
odoo_addon_product_variant_change_attribute_value-18.0.1.0.0.4.dist-info/METADATA
odoo_addon_product_variant_change_attribute_value-18.0.1.0.0.4.dist-info/WHEEL
odoo_addon_product_variant_change_attribute_value-18.0.1.0.0.4.dist-info/top_level.txt
odoo_addon_product_variant_change_attribute_value-18.0.1.0.0.4.dist-info/RECORD
