Metadata-Version: 2.1
Name: odoo-addon-product_variant_change_attribute_value
Version: 18.0.1.0.0.4
Requires-Python: >=3.10
Requires-Dist: odoo==18.0.*
Summary: Product Variant Change Attribute Value
Home-page: https://github.com/OCA/product-variant
License: AGPL-3
Author: Camptocamp SA, Odoo Community Association (OCA)
Author-email: support@odoo-community.org
Classifier: Programming Language :: Python
Classifier: Framework :: Odoo
Classifier: Framework :: Odoo :: 18.0
Classifier: License :: OSI Approved :: GNU Affero General Public License v3
